glc/__init__.py
glc/api/__init__.py
glc/api/base.py
glc/api/gitlab.py
glc/api/ns.py
glc/api/project.py
glc/api/user.py
glc/cli/__init__.py
glc/cli/entry.py
glc/cli/subs/__init__.py
glc/cli/subs/c_config.py
glc/cli/subs/c_group.py
glc/cli/subs/c_info.py
glc/cli/subs/c_issue.py
glc/cli/subs/c_mr.py
glc/cli/subs/c_ns.py
glc/cli/subs/c_reg.py
glc/cli/subs/c_repo.py
glc/cli/subs/c_snippet.py
glc/cli/subs/c_user.py
glc/config/__init__.py
glc/config/conf.py
glc/utils/__init__.py
glc/utils/error.py
gli/__init__.py
gli/api/__init__.py
gli/api/base.py
gli/api/gitlab.py
gli/api/ns.py
gli/api/project.py
gli/api/user.py
gli/cli/__init__.py
gli/cli/entry.py
gli/cli/subs/__init__.py
gli/cli/subs/c_config.py
gli/cli/subs/c_group.py
gli/cli/subs/c_info.py
gli/cli/subs/c_issue.py
gli/cli/subs/c_mr.py
gli/cli/subs/c_ns.py
gli/cli/subs/c_reg.py
gli/cli/subs/c_repo.py
gli/cli/subs/c_snippet.py
gli/cli/subs/c_user.py
gli/config/__init__.py
gli/config/conf.py
gli/utils/__init__.py
gli/utils/error.py
glc-0.0.2.dist-info/LICENSE
glc-0.0.2.dist-info/METADATA
glc-0.0.2.dist-info/WHEEL
glc-0.0.2.dist-info/entry_points.txt
glc-0.0.2.dist-info/top_level.txt
glc-0.0.2.dist-info/RECORD
