Metadata-Version: 2.1
Name: glc
Version: 0.0.2
Summary: GitLab command line interface
Home-page: https://github.com/evinoca/glc
Author: Audric Sun
Author-email: audric.s@outlook.com
License: MIT
Project-URL: Documentation, https://gli.readthedocs.io/en/latest/
Project-URL: Changelog, https://github.com/evinoca/glc/blob/release/CHANGELOG.md
Project-URL: Source, https://github.com/evinoca/glc
Project-URL: Tracker, https://github.com/evinoca/glc/issues
Platform: UNKNOWN
Classifier: Development Status :: 2 - Pre-Alpha
Classifier: Environment :: Console
Classifier: Intended Audience :: Developers
Classifier: License :: OSI Approved :: MIT License
Classifier: Operating System :: Microsoft :: Windows
Classifier: Operating System :: MacOS
Classifier: Operating System :: POSIX :: Linux
Classifier: Programming Language :: Python :: 3.6
Classifier: Programming Language :: Python :: 3.7
Classifier: Programming Language :: Python :: 3.8
Requires-Python: >=3.6
Requires-Dist: requests (<3,>=2.20.0)
Requires-Dist: click (>=7)
Requires-Dist: rich (>=1)
Requires-Dist: colorama (<1,>=0.4) ; sys_platform == "win32"
Provides-Extra: tests
Requires-Dist: pytest (>=2.9) ; extra == 'tests'
Requires-Dist: pytest-flake8 (>=1) ; extra == 'tests'
Requires-Dist: pytest-cov ; extra == 'tests'
Requires-Dist: pytest-mock ; extra == 'tests'
